roblox_cloud_api/__init__.py
roblox_cloud_api/account.py
roblox_cloud_api/games.py
roblox_cloud_api/groups.py
roblox_cloud_api/messages.py
roblox_cloud_api/users.py
py_roblox_cloud-0.1.0.dist-info/METADATA
py_roblox_cloud-0.1.0.dist-info/WHEEL
py_roblox_cloud-0.1.0.dist-info/top_level.txt
py_roblox_cloud-0.1.0.dist-info/RECORD
